securicad/aws_collector/__init__.py
securicad/aws_collector/__main__.py
securicad/aws_collector/account_collector.py
securicad/aws_collector/exceptions.py
securicad/aws_collector/py.typed
securicad/aws_collector/region_collector.py
securicad/aws_collector/schemas.py
securicad/aws_collector/utils.py
securicad_aws_collector-2.0.2.dist-info/LICENSE
securicad_aws_collector-2.0.2.dist-info/METADATA
securicad_aws_collector-2.0.2.dist-info/NOTICE
securicad_aws_collector-2.0.2.dist-info/WHEEL
securicad_aws_collector-2.0.2.dist-info/entry_points.txt
securicad_aws_collector-2.0.2.dist-info/top_level.txt
securicad_aws_collector-2.0.2.dist-info/RECORD
