Metadata-Version: 2.1
Name: securicad-aws-collector
Version: 2.0.2
Summary: A Python package for collecting AWS data for use in foreseeti's securiCAD products
Home-page: https://github.com/foreseeti/securicad-aws-collector
Author: Foreseeti AB
License: The Apache Software License, Version 2.0
Keywords: securicad,aws,threat,modeling
Platform: UNKNOWN
Classifier: Environment :: Console
Classifier: Intended Audience :: Developers
Classifier: Intended Audience :: Information Technology
Classifier: Intended Audience :: System Administrators
Classifier: License :: OSI Approved
Classifier: License :: OSI Approved :: Apache Software License
Classifier: Natural Language :: English
Classifier: Operating System :: OS Independent
Classifier: Programming Language :: Python
Classifier: Programming Language :: Python :: 3
Classifier: Programming Language :: Python :: 3 :: Only
Classifier: Programming Language :: Python :: 3.8
Classifier: Programming Language :: Python :: 3.9
Classifier: Programming Language :: Python :: 3.10
Classifier: Topic :: Security
Classifier: Topic :: Software Development
Classifier: Topic :: Software Development :: Libraries
Classifier: Topic :: Software Development :: Libraries :: Application Frameworks
Classifier: Topic :: Software Development :: Libraries :: Python Modules
Classifier: Typing :: Typed
Requires-Python: >=3.8
License-File: LICENSE
License-File: NOTICE
Requires-Dist: boto3
Requires-Dist: botocore
Requires-Dist: jsonschema
Requires-Dist: typer
Provides-Extra: dev
Requires-Dist: black ; extra == 'dev'
Requires-Dist: boto3-stubs ; extra == 'dev'
Requires-Dist: build ; extra == 'dev'
Requires-Dist: isort ; extra == 'dev'
Requires-Dist: mypy ; extra == 'dev'
Requires-Dist: pylint ; extra == 'dev'
Requires-Dist: twine ; extra == 'dev'
Requires-Dist: types-jsonschema ; extra == 'dev'
